{
  "antisynergy": "complete_map",
  "criteria": {
    "complete": {
      "conditions": {
        "scale": {
          "min": 4
        }
      },
      "trigger": "bingo:completed_map"
    }
  },
  "difficulty": "bingo:hard",
  "icon": {
    "type": "bingo:item",
    "item": {
      "Count": 1,
      "id": "minecraft:filled_map"
    }
  },
  "name": {
    "translate": "bingo.goal.complete_full_size_map"
  },
  "requirements": [
    [
      "complete"
    ]
  ],
  "tags": [
    "bingo:action",
    "bingo:overworld"
  ]
}