{
  "criteria": {
    "feed": {
      "conditions": {
        "entity": [
          {
            "condition": "minecraft:entity_properties",
            "entity": "this",
            "predicate": {
              "type": "minecraft:panda"
            }
          }
        ],
        "item": {
          "items": [
            "minecraft:cake"
          ]
        }
      },
      "trigger": "minecraft:thrown_item_picked_up_by_entity"
    }
  },
  "difficulty": 3,
  "icon": {
    "type": "bingo:item",
    "value": {
      "Count": 1,
      "id": "minecraft:panda_spawn_egg"
    }
  },
  "name": {
    "translate": "bingo.goal.feed_panda_cake",
    "with": [
      {
        "translate": "entity.minecraft.panda"
      },
      {
        "translate": "block.minecraft.cake"
      }
    ]
  },
  "requirements": [
    [
      "feed"
    ]
  ],
  "tags": [
    "bingo:action",
    "bingo:overworld",
    "bingo:rare_biome"
  ]
}