{
  "antisynergy": "never_wear_armor",
  "catalyst": "wear_armor",
  "criteria": {
    "equip": {
      "conditions": {
        "new_item": {
          "tag": "bingo:armor"
        },
        "slots": []
      },
      "trigger": "bingo:equip_item"
    }
  },
  "difficulty": 2,
  "icon": {
    "type": "bingo:item",
    "value": {
      "Count": 1,
      "id": "minecraft:diamond_chestplate",
      "tag": {
        "Damage": 0
      }
    }
  },
  "name": {
    "translate": "bingo.goal.never_wear_armor"
  },
  "requirements": [
    [
      "equip"
    ]
  ],
  "tags": [
    "bingo:never"
  ]
}