{
  "criteria": {
    "pickup": {
      "conditions": {
        "item_entity": [
          {
            "condition": "minecraft:entity_properties",
            "entity": "this",
            "predicate": {
              "type_specific": {
                "type": "bingo:item",
                "dropped_by": {
                  "type": "minecraft:skeleton"
                },
                "item": {
                  "items": [
                    "minecraft:bow"
                  ]
                }
              }
            }
          }
        ]
      },
      "trigger": "bingo:item_picked_up"
    }
  },
  "difficulty": "bingo:medium",
  "icon": {
    "type": "bingo:item",
    "value": {
      "Count": 1,
      "id": "minecraft:bow",
      "tag": {
        "Damage": 0
      }
    }
  },
  "name": {
    "translate": "bingo.goal.skeleton_bow"
  },
  "reactant": "pacifist",
  "requirements": [
    [
      "pickup"
    ]
  ],
  "tags": [
    "bingo:item",
    "bingo:combat"
  ]
}