{
  "antisynergy": "feather",
  "bingo_subs": {
    "count": {
      "type": "bingo:int",
      "value": {
        "type": "minecraft:uniform",
        "value": {
          "max_inclusive": 64,
          "min_inclusive": 32
        }
      }
    }
  },
  "criteria": {
    "obtain": {
      "conditions": {
        "items": [
          {
            "count": {
              "min": {
                "bingo_type": "bingo:sub",
                "value": "count"
              }
            },
            "items": [
              "minecraft:feather"
            ]
          }
        ]
      },
      "trigger": "bingo:total_count_inventory_changed"
    }
  },
  "difficulty": "bingo:easy",
  "icon": {
    "type": "bingo:item",
    "value": {
      "Count": {
        "bingo_type": "bingo:sub",
        "value": "count"
      },
      "id": "minecraft:feather"
    }
  },
  "infrequency": 2,
  "name": {
    "translate": "bingo.count",
    "with": [
      {
        "bingo_type": "bingo:sub",
        "value": "count"
      },
      {
        "translate": "item.minecraft.feather"
      }
    ]
  },
  "progress": {
    "type": "bingo:criterion",
    "criterion": "obtain"
  },
  "requirements": [
    [
      "obtain"
    ]
  ],
  "tags": [
    "bingo:item"
  ]
}